adHarvester/MetaSelector.py
adHarvester/Needle.py
adHarvester/Selector.py
adHarvester/SoupPage.py
adHarvester/__init__.py
adHarvester-0.0.1.dist-info/METADATA
adHarvester-0.0.1.dist-info/WHEEL
adHarvester-0.0.1.dist-info/top_level.txt
adHarvester-0.0.1.dist-info/RECORD
